pystatusbar/__init__.py
pystatusbar/statusbar.py
pystatusbar-0.0.5.dist-info/METADATA
pystatusbar-0.0.5.dist-info/WHEEL
pystatusbar-0.0.5.dist-info/licenses/LICENSE
pystatusbar-0.0.5.dist-info/RECORD
