Metadata-Version: 2.3
Name: pystatusbar
Version: 0.0.5
Summary: Python package to easily create a statusbar that can be modified and expanded with pythons formatted strings
Project-URL: Homepage, https://github.com/lukaswd/statusbar
Project-URL: Issues, https://github.com/lukaswd/statusbar/issues
Author: Lukas Wedi
Classifier: License :: OSI Approved :: MIT License
Classifier: Operating System :: OS Independent
Classifier: Programming Language :: Python :: 3
Requires-Python: >=3.8
